tws_async/__init__.py
tws_async/contracts.py
tws_async/histrequester.py
tws_async/twsclient.py
tws_async/twsclientqt.py
tws_async/util.py
tws_async-0.5.7.data/data/samples/histrequester_demo.py
tws_async-0.5.7.data/data/samples/tickstreamer_demo.py
tws_async-0.5.7.data/data/samples/tws.ipynb
tws_async-0.5.7.dist-info/DESCRIPTION.rst
tws_async-0.5.7.dist-info/METADATA
tws_async-0.5.7.dist-info/RECORD
tws_async-0.5.7.dist-info/WHEEL
tws_async-0.5.7.dist-info/metadata.json
tws_async-0.5.7.dist-info/top_level.txt
