Metadata-Version: 2.0
Name: tws-async
Version: 0.5.7
Summary: Use the Interactive Brokers API (IBAPI) asynchonouslywith asyncio or PyQt5
Home-page: https://github.com/erdewit/tws_async
Author: Ewald R. de Wit
Author-email: ewald.de.wit@gmail.com
License: Freeware
Keywords: ibapi asyncio qt pyqt pyqt5 jupyter interactive brokers async
Platform: UNKNOWN
Classifier: Development Status :: 4 - Beta
Classifier: Intended Audience :: Developers
Classifier: Topic :: Office/Business :: Financial :: Investment
Classifier: License :: Freeware
Classifier: Programming Language :: Python :: 3.5
Classifier: Programming Language :: Python :: 3.6
Classifier: Programming Language :: Python :: 3 :: Only
Requires-Dist: PyQt5
Requires-Dist: jupyter
Requires-Dist: numpy
Requires-Dist: pandas
Requires-Dist: pytz
Requires-Dist: quamash
Requires-Dist: seaborn
